CHANGES.txt
LICENSE.txt
MANIFEST.in
README.rst
conf.py
index.rst
setup.py
dirtyjson/__init__.py
dirtyjson/attributed_containers.py
dirtyjson/compat.py
dirtyjson/error.py
dirtyjson/loader.py
dirtyjson.egg-info/PKG-INFO
dirtyjson.egg-info/SOURCES.txt
dirtyjson.egg-info/dependency_links.txt
dirtyjson.egg-info/top_level.txt
dirtyjson.egg-info/zip-safe
dirtyjson/tests/__init__.py
dirtyjson/tests/test_decimal.py
dirtyjson/tests/test_decode.py
dirtyjson/tests/test_errors.py
dirtyjson/tests/test_fail.py
dirtyjson/tests/test_float.py
dirtyjson/tests/test_integer.py
dirtyjson/tests/test_pass1.py
dirtyjson/tests/test_pass2.py
dirtyjson/tests/test_pass3.py
dirtyjson/tests/test_unicode.py
scripts/make_docs.py